Workbook

Sheet Summary
A1: JSE price reconciliation: break report
A2: As of 2026-09-11. Generated 2026-09-30 10:57 SAST. Every count below is a formula over the tab named beside it.
A4: Breaks between sources
A5: Open breaks | B5: =SUM(B6:B9) -> 19 | C5: Open Breaks tab
A6: open 0-1 days | B6: =COUNTIFS('Open Breaks'!$I:$I,"0-1 days") -> 19 | C6: Open Breaks tab
A7: open 2-5 days | B7: =COUNTIFS('Open Breaks'!$I:$I,"2-5 days") -> 0 | C7: Open Breaks tab
A8: open 6-20 days | B8: =COUNTIFS('Open Breaks'!$I:$I,"6-20 days") -> 0 | C8: Open Breaks tab
A9: open 21+ days | B9: =COUNTIFS('Open Breaks'!$I:$I,"21+ days") -> 0 | C9: Open Breaks tab
A10: New in the latest comparison | B10: =COUNTA('New Today'!$B:$B)-1 -> 2 | C10: New Today tab
A11: Cleared as timing differences | B11: =COUNTIFS(Cleared!$J:$J,"TIMING") -> 11 | C11: Cleared tab
A12: Cleared after longer | B12: =COUNTIFS(Cleared!$J:$J,"CLEARED") -> 0 | C12: Cleared tab
A13: Mean trading days to clear | B13: =IFERROR(AVERAGE(Cleared!$I:$I),"-") -> 1 | C13: Cleared tab
A14: Open breaks over 50% (scale) | B14: =COUNTIFS('Open Breaks'!$J:$J,"SCALE") -> 9 | C14: Open Breaks tab
A15: Largest open cost in a Top 40 fund | B15: =MAX(MAX('Open Breaks'!$U:$U),-MIN('Open Breaks'!$U:$U)) -> 0.1188 | C15: Open Breaks tab
A16: Restatements since the previous snapshot
A17: Prices rewritten | B17: =COUNTIFS(Restatements!$C:$C,"VAL")+COUNTIFS(Restatements!$C:$C,"UNIT")+COUNTIFS(Restatements!$C:$C,"STALE")+COUNTIFS(Restatements!$C:$C,"SCALE") -> 1 | C17: Restatements tab
A18: Prices published late | B18: =COUNTIFS(Restatements!$C:$C,"ONE_B") -> 12 | C18: Restatements tab
A19: Prices withdrawn | B19: =COUNTIFS(Restatements!$C:$C,"ONE_A") -> 0 | C19: Restatements tab
A20: Data quality, latest full snapshot
A21: Unit anomalies | B21: =COUNTIFS('Data Quality'!$A:$A,"Unit anomaly") -> 1 | C21: Data Quality tab
A22: Missing sessions | B22: =COUNTIFS('Data Quality'!$A:$A,"Missing session") -> 0 | C22: Data Quality tab
A23: Missing prices | B23: =COUNTIFS('Data Quality'!$A:$A,"Missing price") -> 2 | C23: Data Quality tab
A24: Frozen prices | B24: =COUNTIFS('Data Quality'!$A:$A,"Frozen price") -> 1 | C24: Data Quality tab
A25: Prices on closed days | B25: =COUNTIFS('Data Quality'!$A:$A,"Price on closed day") -> 1 | C25: Data Quality tab
A26: Broker statement against the internal book
A27: Positions compared | B27: =COUNTA(Holdings!$B:$B)-1 -> 0 | C27: Holdings tab
A28: Positions agreeing | B28: =COUNTIFS(Holdings!$B:$B,"MATCH") -> 0 | C28: Holdings tab
A29: Holdings breaks | B29: =COUNTA(Holdings!$B:$B)-1-COUNTIFS(Holdings!$B:$B,"MATCH") -> 0 | C29: Holdings tab
A30: Net difference (R) | B30: =SUM(Holdings!$L:$L) -> 0 | C30: Holdings tab
A31: Gross difference (R) | B31: =SUMPRODUCT(ABS(Holdings!$L$2:$L$2000)) -> 0 | C31: Holdings tab
A32: of which errors (R) | B32: =SUMPRODUCT(ABS(Holdings!$L$2:$L$2000)*(Holdings!$B$2:$B$2000<>"MATCH")*(Holdings!$B$2:$B$2000<>"SETTLE")) -> 0 | C32: Holdings tab
A33: of which timing differences (R) | B33: =SUMPRODUCT(ABS(Holdings!$L$2:$L$2000)*(Holdings!$B$2:$B$2000="SETTLE")) -> 0 | C33: Holdings tab
A34: Positions that could not be valued | B34: =SUMPRODUCT((Holdings!$B$2:$B$2000<>"")*(Holdings!$L$2:$L$2000="")) -> 0 | C34: Holdings tab

Sheet Open Breaks
A1: Recon | B1: Security | C1: Name | D1: Sector | E1: Price date | F1: First seen | G1: Last seen | H1: Age (trading days) | I1: Age bucket | J1: Status | K1: Close A (R) | L1: Close B (R) | M1: Difference (R) | N1: Difference (%) | O1: Explanation | P1: Resolution | Q1: Note | R1: Age from price date | S1: Found on first comparison | T1: Top 40 weight | U1: Cost in a Top 40 fund
A2: synthetic_a_vs_synthetic_b | B2: SYJ | C2: Synthetic Kappa Ltd (fictional) | D2: Basic Materials | E2: 46244 | F2: 46275 | G2: 46276 | H2: 1 | I2: =IF(H2<=1,"0-1 days",IF(H2<=5,"2-5 days",IF(H2<=20,"6-20 days","21+ days"))) -> 0-1 days | J2: CAL | L2: 102.4939 | O2: One side has a bar on a day the JSE was closed | R2: 24 | S2: Yes | T2: 0.04 | U2: =IF(OR(T2="",K2="",L2=""),"",T2*ABS(M2)/MAX(K2,L2))
A3: synthetic_a_vs_synthetic_b | B3: SYC | C3: Synthetic Gamma Ltd (fictional) | D3: Technology | E3: 46254 | F3: 46275 | G3: 46276 | H3: 1 | I3: =IF(H3<=1,"0-1 days",IF(H3<=5,"2-5 days",IF(H3<=20,"6-20 days","21+ days"))) -> 0-1 days | J3: UNIT | K3: 0.301812 | L3: 30.1812 | M3: 29.879388 | N3: 99 | O3: Unit anomaly flagged in staging; B/A = 100.0000 | R3: 16 | S3: Yes | T3: 0.12 | U3: =IF(OR(T3="",K3="",L3=""),"",T3*ABS(M3)/MAX(K3,L3)) -> 0.1188
A4: synthetic_a_vs_synthetic_b | B4: SYI | C4: Synthetic Iota Ltd (fictional) | D4: Financials | E4: 46273 | F4: 46275 | G4: 46276 | H4: 1 | I4: =IF(H4<=1,"0-1 days",IF(H4<=5,"2-5 days",IF(H4<=20,"6-20 days","21+ days"))) -> 0-1 days | J4: SCALE | K4: 79.8234 | L4: 0.498896 | M4: -79.324504 | N4: -0.99375 | O4: Differs by R-79.32 (-99.38%): the sources disagree on scale, B/A = 0.0062 | R4: 3 | S4: Yes | T4: 0.05 | U4: =IF(OR(T4="",K4="",L4=""),"",T4*ABS(M4)/MAX(K4,L4)) -> 0.0496875
A5: synthetic_a_vs_synthetic_b | B5: SYI | C5: Synthetic Iota Ltd (fictional) | D5: Financials | E5: 46268 | F5: 46275 | G5: 46276 | H5: 1 | I5: =IF(H5<=1,"0-1 days",IF(H5<=5,"2-5 days",IF(H5<=20,"6-20 days","21+ days"))) -> 0-1 days | J5: SCALE | K5: 80.6258 | L5: 0.503911 | M5: -80.121889 | N5: -0.99375 | O5: Differs by R-80.12 (-99.38%): the sources disagree on scale, B/A = 0.0062 | R5: 6 | S5: Yes | T5: 0.05 | U5: =IF(OR(T5="",K5="",L5=""),"",T5*ABS(M5)/MAX(K5,L5)) -> 0.0496875
A6: synthetic_a_vs_synthetic_b | B6: SYI | C6: Synthetic Iota Ltd (fictional) | D6: Financials | E6: 46274 | F6: 46275 | G6: 46276 | H6: 1 | I6: =IF(H6<=1,"0-1 days",IF(H6<=5,"2-5 days",IF(H6<=20,"6-20 days","21+ days"))) -> 0-1 days | J6: SCALE | K6: 79.7437 | L6: 0.498398 | M6: -79.245302 | N6: -0.99375 | O6: Differs by R-79.25 (-99.38%): the sources disagree on scale, B/A = 0.0062 | R6: 2 | S6: Yes | T6: 0.05 | U6: =IF(OR(T6="",K6="",L6=""),"",T6*ABS(M6)/MAX(K6,L6)) -> 0.0496875
A7: synthetic_a_vs_synthetic_b | B7: SYI | C7: Synthetic Iota Ltd (fictional) | D7: Financials | E7: 46269 | F7: 46275 | G7: 46276 | H7: 1 | I7: =IF(H7<=1,"0-1 days",IF(H7<=5,"2-5 days",IF(H7<=20,"6-20 days","21+ days"))) -> 0-1 days | J7: SCALE | K7: 79.8205 | L7: 0.498878 | M7: -79.321622 | N7: -0.99375 | O7: Differs by R-79.32 (-99.38%): the sources disagree on scale, B/A = 0.0062 | R7: 5 | S7: Yes | T7: 0.05 | U7: =IF(OR(T7="",K7="",L7=""),"",T7*ABS(M7)/MAX(K7,L7)) -> 0.0496875
A8: synthetic_a_vs_synthetic_b | B8: SYI | C8: Synthetic Iota Ltd (fictional) | D8: Financials | E8: 46266 | F8: 46275 | G8: 46276 | H8: 1 | I8: =IF(H8<=1,"0-1 days",IF(H8<=5,"2-5 days",IF(H8<=20,"6-20 days","21+ days"))) -> 0-1 days | J8: SCALE | K8: 89.5808 | L8: 0.55988 | M8: -89.02092 | N8: -0.99375 | O8: Differs by R-89.02 (-99.37%): the sources disagree on scale, B/A = 0.0063 | R8: 8 | S8: Yes | T8: 0.05 | U8: =IF(OR(T8="",K8="",L8=""),"",T8*ABS(M8)/MAX(K8,L8)) -> 0.0496875
A9: synthetic_a_vs_synthetic_b | B9: SYI | C9: Synthetic Iota Ltd (fictional) | D9: Financials | E9: 46267 | F9: 46275 | G9: 46276 | H9: 1 | I9: =IF(H9<=1,"0-1 days",IF(H9<=5,"2-5 days",IF(H9<=20,"6-20 days","21+ days"))) -> 0-1 days | J9: SCALE | K9: 89.9094 | L9: 0.561934 | M9: -89.347466 | N9: -0.99375 | O9: Differs by R-89.35 (-99.37%): the sources disagree on scale, B/A = 0.0063 | R9: 7 | S9: Yes | T9: 0.05 | U9: =IF(OR(T9="",K9="",L9=""),"",T9*ABS(M9)/MAX(K9,L9)) -> 0.0496875
A10: synthetic_a_vs_synthetic_b | B10: SYI | C10: Synthetic Iota Ltd (fictional) | D10: Financials | E10: 46276 | F10: 46276 | G10: 46276 | H10: 0 | I10: =IF(H10<=1,"0-1 days",IF(H10<=5,"2-5 days",IF(H10<=20,"6-20 days","21+ days"))) -> 0-1 days | J10: SCALE | K10: 78.8494 | L10: 0.492809 | M10: -78.356591 | N10: -0.99375 | O10: Differs by R-78.36 (-99.37%): the sources disagree on scale, B/A = 0.0063 | R10: 0 | S10: No | T10: 0.05 | U10: =IF(OR(T10="",K10="",L10=""),"",T10*ABS(M10)/MAX(K10,L10)) -> 0.0496875
A11: synthetic_a_vs_synthetic_b | B11: SYI | C11: Synthetic Iota Ltd (fictional) | D11: Financials | E11: 46272 | F11: 46275 | G11: 46276 | H11: 1 | I11: =IF(H11<=1,"0-1 days",IF(H11<=5,"2-5 days",IF(H11<=20,"6-20 days","21+ days"))) -> 0-1 days | J11: SCALE | K11: 79.5041 | L11: 0.496901 | M11: -79.007199 | N11: -0.99375 | O11: Differs by R-79.01 (-99.37%): the sources disagree on scale, B/A = 0.0063 | R11: 4 | S11: Yes | T11: 0.05 | U11: =IF(OR(T11="",K11="",L11=""),"",T11*ABS(M11)/MAX(K11,L11)) -> 0.0496875
A12: synthetic_a_vs_synthetic_b | B12: SYI | C12: Synthetic Iota Ltd (fictional) | D12: Financials | E12: 46275 | F12: 46275 | G12: 46276 | H12: 1 | I12: =IF(H12<=1,"0-1 days",IF(H12<=5,"2-5 days",IF(H12<=20,"6-20 days","21+ days"))) -> 0-1 days | J12: SCALE | K12: 79.2484 | L12: 0.495303 | M12: -78.753097 | N12: -0.99374999 | O12: Differs by R-78.75 (-99.37%): the sources disagree on scale, B/A = 0.0063 | R12: 1 | S12: Yes | T12: 0.05 | U12: =IF(OR(T12="",K12="",L12=""),"",T12*ABS(M12)/MAX(K12,L12)) -> 0.0496875
A13: synthetic_a_vs_synthetic_b | B13: SYB | C13: Synthetic Beta Ltd (fictional) | D13: Basic Materials | E13: 46266 | F13: 46276 | G13: 46276 | H13: 0 | I13: =IF(H13<=1,"0-1 days",IF(H13<=5,"2-5 days",IF(H13<=20,"6-20 days","21+ days"))) -> 0-1 days | J13: VAL | K13: 20.6397 | L13: 20.235 | M13: -0.4047 | N13: -0.019607843 | O13: Differs by R-0.40 (-1.96%), over both R0.01 and 0.05% | R13: 8 | S13: No | T13: 0.15 | U13: =IF(OR(T13="",K13="",L13=""),"",T13*ABS(M13)/MAX(K13,L13)) -> 0.0029411765
A14: synthetic_a_vs_synthetic_b | B14: SYE | C14: Synthetic Epsilon Ltd (fictional) | D14: Financials | E14: 46253 | F14: 46275 | G14: 46276 | H14: 1 | I14: =IF(H14<=1,"0-1 days",IF(H14<=5,"2-5 days",IF(H14<=20,"6-20 days","21+ days"))) -> 0-1 days | J14: STALE | K14: 49.7292 | L14: 50.2582 | M14: 0.529 | N14: 0.010637613 | O14: Differs by R0.53 (1.06%); one side unchanged for 6 sessions | R14: 17 | S14: Yes | T14: 0.08 | U14: =IF(OR(T14="",K14="",L14=""),"",T14*ABS(M14)/MAX(K14,L14)) -> 0.00084205165
... A20: synthetic_a_vs_synthetic_b | B20: SYE | C20: Synthetic Epsilon Ltd (fictional) | D20: Financials | E20: 46247 | F20: 46275 | G20: 46276 | H20: 1 | I20: =IF(H20<=1,"0-1 days",IF(H20<=5,"2-5 days",IF(H20<=20,"6-20 days","21+ days"))) -> 0-1 days | J20: VAL | K20: 49.7292 | L20: 49.6712 | M20: -0.058 | N20: -0.0011663168 | O20: Differs by R-0.06 (-0.12%), over both R0.01 and 0.05% | R20: 21 | S20: Yes | T20: 0.08 | U20: =IF(OR(T20="",K20="",L20=""),"",T20*ABS(M20)/MAX(K20,L20)) -> 9.3305342e-05

Sheet New Today
A1: Recon | B1: Security | C1: Name | D1: Price date | E1: Status | F1: Close A (R) | G1: Close B (R) | H1: Difference (R) | I1: Difference (%) | J1: Explanation | K1: State
A2: synthetic_a_vs_synthetic_b | B2: SYB | C2: Synthetic Beta Ltd (fictional) | D2: 46266 | E2: VAL | F2: 20.6397 | G2: 20.235 | H2: -0.4047 | I2: -0.019607843 | J2: Differs by R-0.40 (-1.96%), over both R0.01 and 0.05% | K2: OPEN
A3: synthetic_a_vs_synthetic_b | B3: SYI | C3: Synthetic Iota Ltd (fictional) | D3: 46276 | E3: SCALE | F3: 78.8494 | G3: 0.492809 | H3: -78.356591 | I3: -0.99375 | J3: Differs by R-78.36 (-99.37%): the sources disagree on scale, B/A = 0.0063 | K3: OPEN

Sheet Cleared
A1: Recon | B1: Security | C1: Name | D1: Price date | E1: First seen | F1: Cleared on | G1: Comparisons | H1: First status | I1: Age (trading days) | J1: State | K1: Last explanation | L1: Resolution | M1: Note
A2: synthetic_a_vs_synthetic_b | B2: SYA | C2: Synthetic Alpha Ltd (fictional) | D2: 46275 | E2: 46275 | F2: 46276 | G2: 1 | H2: ONE_B | I2: 1 | J2: TIMING | K2: In B only
A3: synthetic_a_vs_synthetic_b | B3: SYB | C3: Synthetic Beta Ltd (fictional) | D3: 46275 | E3: 46275 | F3: 46276 | G3: 1 | H3: ONE_B | I3: 1 | J3: TIMING | K3: In B only
A4: synthetic_a_vs_synthetic_b | B4: SYC | C4: Synthetic Gamma Ltd (fictional) | D4: 46275 | E4: 46275 | F4: 46276 | G4: 1 | H4: ONE_B | I4: 1 | J4: TIMING | K4: In B only
A5: synthetic_a_vs_synthetic_b | B5: SYD | C5: Synthetic Delta Ltd (fictional) | D5: 46275 | E5: 46275 | F5: 46276 | G5: 1 | H5: ONE_B | I5: 1 | J5: TIMING | K5: In B only
A6: synthetic_a_vs_synthetic_b | B6: SYE | C6: Synthetic Epsilon Ltd (fictional) | D6: 46275 | E6: 46275 | F6: 46276 | G6: 1 | H6: ONE_B | I6: 1 | J6: TIMING | K6: In B only
A7: synthetic_a_vs_synthetic_b | B7: SYF | C7: Synthetic Zeta Ltd (fictional) | D7: 46275 | E7: 46275 | F7: 46276 | G7: 1 | H7: ONE_B | I7: 1 | J7: TIMING | K7: In B only
A8: synthetic_a_vs_synthetic_b | B8: SYG | C8: Synthetic Eta Ltd (fictional) | D8: 46275 | E8: 46275 | F8: 46276 | G8: 1 | H8: ONE_B | I8: 1 | J8: TIMING | K8: In B only
A9: synthetic_a_vs_synthetic_b | B9: SYH | C9: Synthetic Theta Ltd (fictional) | D9: 46275 | E9: 46275 | F9: 46276 | G9: 1 | H9: ONE_B | I9: 1 | J9: TIMING | K9: In B only
A10: synthetic_a_vs_synthetic_b | B10: SYJ | C10: Synthetic Kappa Ltd (fictional) | D10: 46275 | E10: 46275 | F10: 46276 | G10: 1 | H10: ONE_B | I10: 1 | J10: TIMING | K10: In B only
A11: synthetic_a_vs_synthetic_b | B11: SYK | C11: Synthetic Lambda Ltd (fictional) | D11: 46275 | E11: 46275 | F11: 46276 | G11: 1 | H11: ONE_B | I11: 1 | J11: TIMING | K11: In B only
A12: synthetic_a_vs_synthetic_b | B12: SYL | C12: Synthetic Mu Ltd (fictional) | D12: 46275 | E12: 46275 | F12: 46276 | G12: 1 | H12: ONE_B | I12: 1 | J12: TIMING | K12: In B only

Sheet Restatements
A1: Security | B1: Price date | C1: Status | D1: Close in 2026-09-10 snapshot (R) | E1: Close in 2026-09-11 snapshot (R) | F1: Difference (R) | G1: Explanation
A2: SYB | B2: 46266 | C2: VAL | D2: 20.235 | E2: 20.6397 | F2: 0.4047 | G2: Differs by R0.40 (2.00%), over both R0.01 and 0.01%
A3: SYA | B3: 46275 | C3: ONE_B | E3: 8.5413 | G3: In B only
A4: SYB | B4: 46275 | C4: ONE_B | E4: 18.4138 | G4: In B only
A5: SYC | B5: 46275 | C5: ONE_B | E5: 28.1282 | G5: In B only
A6: SYD | B6: 46275 | C6: ONE_B | E6: 48.4189 | G6: In B only
A7: SYE | B7: 46275 | C7: ONE_B | E7: 44.3919 | G7: In B only
A8: SYF | B8: 46275 | C8: ONE_B | E8: 55.7312 | G8: In B only
A9: SYG | B9: 46275 | C9: ONE_B | E9: 62.2266 | G9: In B only
A10: SYH | B10: 46275 | C10: ONE_B | E10: 69.0828 | G10: In B only
A11: SYI | B11: 46275 | C11: ONE_B | E11: 79.2484 | G11: In B only
A12: SYJ | B12: 46275 | C12: ONE_B | E12: 96.3414 | G12: In B only
A13: SYK | B13: 46275 | C13: ONE_B | E13: 1005.9954 | G13: In B only
A14: SYL | B14: 46275 | C14: ONE_B | E14: 106.2101 | G14: In B only

Sheet Data Quality
A1: Check | B1: Security | C1: Date | D1: Detail | E1: Source
A2: Unit anomaly | B2: SYC | C2: 46254 | D2: R0.30, about 100x below its nearest bars (R30.15 and R29.97) | E2: synthetic_a
A3: Missing price | B3: SYL | C3: 46265 | D3: No price on a trading day | E3: synthetic_a
A4: Frozen price | B4: SYE | C4: 46253 | D4: R49.73 unchanged for 6 sessions | E4: synthetic_a
A5: Missing price | B5: SYL | C5: 46265 | D5: No price on a trading day | E5: synthetic_b
A6: Price on closed day | B6: All | C6: 46244 | D6: 1 prices on National Women's Day (observed), 1 with volume | E6: synthetic_b

Sheet Holdings
A1: Security | B1: Status | C1: Statement lines | D1: Broker value (R) | E1: Broker price (R) | F1: Implied quantity | G1: Book quantity | H1: Settled quantity | I1: Our close (R) | J1: Previous close (R) | K1: Book at our close (R) | L1: Difference (R) | M1: Explanation
A2: No broker statement loaded

Sheet Approved Prices
A1: Security | B1: Name | C1: Price to use (R) | D1: Source | E1: Status | F1: Why | H1: For 2026-09-11; exceptions first
A2: SYI | B2: Synthetic Iota Ltd (fictional) | C2: 78.8494 | D2: synthetic_a | E2: TO_VERIFY | F2: The sources disagree and the break has no resolution yet: confirm before use
A3: SYA | B3: Synthetic Alpha Ltd (fictional) | C3: 8.4601 | D3: synthetic_a | E3: APPROVED | F3: Primary source, passed every check
A4: SYB | B4: Synthetic Beta Ltd (fictional) | C4: 18.413 | D4: synthetic_a | E4: APPROVED | F4: Primary source, passed every check
A5: SYC | B5: Synthetic Gamma Ltd (fictional) | C5: 27.8788 | D5: synthetic_a | E5: APPROVED | F5: Primary source, passed every check
A6: SYD | B6: Synthetic Delta Ltd (fictional) | C6: 48.253 | D6: synthetic_a | E6: APPROVED | F6: Primary source, passed every check
A7: SYE | B7: Synthetic Epsilon Ltd (fictional) | C7: 44.6065 | D7: synthetic_a | E7: APPROVED | F7: Primary source, passed every check
A8: SYF | B8: Synthetic Zeta Ltd (fictional) | C8: 55.5231 | D8: synthetic_a | E8: APPROVED | F8: Primary source, passed every check
A9: SYG | B9: Synthetic Eta Ltd (fictional) | C9: 62.2997 | D9: synthetic_a | E9: APPROVED | F9: Primary source, passed every check
A10: SYH | B10: Synthetic Theta Ltd (fictional) | C10: 68.934 | D10: synthetic_a | E10: APPROVED | F10: Primary source, passed every check
A11: SYJ | B11: Synthetic Kappa Ltd (fictional) | C11: 95.5223 | D11: synthetic_a | E11: APPROVED | F11: Primary source, passed every check
A12: SYK | B12: Synthetic Lambda Ltd (fictional) | C12: 1009.3901 | D12: synthetic_a | E12: APPROVED | F12: Primary source, passed every check
A13: SYL | B13: Synthetic Mu Ltd (fictional) | C13: 106.0873 | D13: synthetic_a | E13: APPROVED | F13: Primary source, passed every check

Sheet Answers
A1: Can synthetic_a be trusted to value a fund of JSE shares?
A2: Evidence: snapshot 2026-09-11, 347 closing prices for 12 securities, 2026-08-03 to 2026-09-11.
A4: 1. Are the prices right?
A5: No. Of all 347 stored prices, 2026-08-03 to 2026-09-11, each as the latest snapshot holding it has it, 1 (0.288%) were about 100x wrong, on 1 days: 2026-08-20 (1 securities).
A6: Separately, 2 day-on-day moves of 15% or more that the median share did not share (by 10% or more). These are not errors in themselves: each needs checking against company news before the price is used. The feed's adjusted close did not adjust 2 of them, so it cannot tell a corporate action from an error.
A7: 2. What would those errors have cost?
A8: For any fund: a price 100x too small understates the fund by 99% of that holding's weight, so a single holding above 0.51% of the fund breaches the 0.5% ASISA tolerance on its own.
A9: Worst day for a Top 40 fund, 2026-08-20: 1,188bp (11.88% of NAV), 23.8x the tolerance, from SYC. Basis: SYNTHETIC weights at 2025-12-31.
A10: Illustrative, equal-weighted across all 12 securities priced on 2026-08-20: 825bp (8.25%).
A11: A unit check or a day-on-day movement check catches errors this large. The cost is what a fund valued from the raw feed, without those controls, would have shown.
A12: 3. Is every trading day there?
A13: Yes, all 29 trading days in the JSE calendar are present.
... A65: Each share's price, source and reason are on the Approved Prices tab of the report.

Sheet About
A1: As of | B1: 2026-09-11
A2: Generated | B2: 2026-09-30 10:57 SAST
A3: Latest synthetic_a snapshot | B3: 2026-09-11, sessions complete to 2026-09-11
A4: Latest synthetic_b snapshot | B4: 2026-09-11, sessions complete to 2026-09-11
A5: Tolerance, yahoo_vs_eodhd | B5: A break needs more than R0.01 and 0.05% difference in the close
A6: Tolerance, yahoo_vs_afx | B6: A break needs more than R0.01 and 0.05% difference in the close
A7: Tolerance, eodhd_vs_afx | B7: A break needs more than R0.01 and 0.05% difference in the close
A8: Tolerance, yahoo_restatement | B8: A break needs more than R0.01 and 0.01% difference in the close
A9: Tolerance, synthetic_a_vs_synthetic_b | B9: A break needs more than R0.01 and 0.05% difference in the close
A10: Tolerance, synthetic_a_restatement | B10: A break needs more than R0.01 and 0.01% difference in the close
A11: Tolerance, synthetic_b_restatement | B11: A break needs more than R0.01 and 0.01% difference in the close
A12: Age | B12: Trading days on the JSE calendar, from first sighting to clearing or to the latest comparison
... A18: Notes | B18: Resolutions and analyst notes come from config/break_notes.yaml in the repository
A20: Break codes
A21: MATCH | B21: Both sides agree within tolerance
A22: VAL | B22: Both sides have a price and they differ by more than both the rand floor and the percentage
A23: ONE_A | B23: Only side A has a price for this security and date
A24: ONE_B | B24: Only side B has a price; in a restatement recon, a price published late
A25: DUP | B25: A side has more than one row for the same security and date
A26: UNIT | B26: The sides are about 100x apart, or one side's unit is flagged or unknown
A27: CAL | B27: A price on a day the JSE was closed
A28: STALE | B28: A value break where one side's price has not moved for 5 or more sessions
A29: SCALE | B29: The sides are more than 50% apart but not about 100x: a different instrument or scale
A30: TIMING | B30: A break that cleared within 2 trading days of first being seen
